{
 "updated": "2026-06-21 20:33",
 "plan": [
  {
   "code": "2559",
   "price": 2968.0,
   "high1y": 2983.0,
   "drawdown": -0.5,
   "yield_pct": null,
   "adjusted": true,
   "days_since_jump": 9,
   "name": "オルカン（全世界株）",
   "target": 0.4
  },
  {
   "code": "1489",
   "price": 3243.0,
   "high1y": 3357.1,
   "drawdown": -3.4,
   "yield_pct": 2.81,
   "adjusted": false,
   "days_since_jump": null,
   "name": "日経高配当株50 ETF",
   "target": 0.1
  },
  {
   "code": "9432",
   "price": 144.4,
   "high1y": 160.0,
   "drawdown": -9.8,
   "yield_pct": 3.67,
   "adjusted": false,
   "days_since_jump": null,
   "name": "NTT",
   "target": 0.1
  },
  {
   "code": "8058",
   "price": 4540.0,
   "high1y": 5882.0,
   "drawdown": -22.8,
   "yield_pct": 2.42,
   "adjusted": false,
   "days_since_jump": null,
   "name": "三菱商事",
   "target": 0.1
  },
  {
   "code": "8766",
   "price": 7194.0,
   "high1y": 7949.0,
   "drawdown": -9.5,
   "yield_pct": 3.03,
   "adjusted": false,
   "days_since_jump": null,
   "name": "東京海上",
   "target": 0.1
  },
  {
   "code": "1540",
   "price": 19990.0,
   "high1y": 26500.0,
   "drawdown": -24.6,
   "yield_pct": null,
   "adjusted": false,
   "days_since_jump": null,
   "name": "金（ゴールド）",
   "target": 0.2
  }
 ],
 "crypto": [
  {
   "code": "BTC",
   "name": "ビットコイン",
   "price": 10365784,
   "high1y": 18838562,
   "drawdown": -45.0,
   "vs_ma": -1.4,
   "ret7": -1.4
  },
  {
   "code": "ETH",
   "name": "イーサリアム",
   "price": 278021,
   "high1y": 710063,
   "drawdown": -60.8,
   "vs_ma": -1.9,
   "ret7": 0.8
  }
 ]
}