{
 "updated": "2026-07-08 14:40",
 "plan": [
  {
   "code": "2559",
   "price": 2986.0,
   "high1y": 2994.0,
   "drawdown": -0.3,
   "yield_pct": null,
   "adjusted": true,
   "days_since_jump": 22,
   "name": "オルカン（全世界株）",
   "target": 0.4
  },
  {
   "code": "1489",
   "price": 3295.0,
   "high1y": 3348.0,
   "drawdown": -1.6,
   "yield_pct": 2.85,
   "adjusted": false,
   "days_since_jump": null,
   "name": "日経高配当株50 ETF",
   "target": 0.1
  },
  {
   "code": "9432",
   "price": 150.4,
   "high1y": 160.0,
   "drawdown": -6.0,
   "yield_pct": 3.52,
   "adjusted": false,
   "days_since_jump": null,
   "name": "NTT",
   "target": 0.1
  },
  {
   "code": "8058",
   "price": 4495.0,
   "high1y": 5882.0,
   "drawdown": -23.6,
   "yield_pct": 2.45,
   "adjusted": false,
   "days_since_jump": null,
   "name": "三菱商事",
   "target": 0.1
  },
  {
   "code": "8766",
   "price": 7737.0,
   "high1y": 7949.0,
   "drawdown": -2.7,
   "yield_pct": 2.82,
   "adjusted": false,
   "days_since_jump": null,
   "name": "東京海上",
   "target": 0.1
  },
  {
   "code": "1540",
   "price": 20055.0,
   "high1y": 26500.0,
   "drawdown": -24.3,
   "yield_pct": null,
   "adjusted": false,
   "days_since_jump": null,
   "name": "金（ゴールド）",
   "target": 0.2
  }
 ],
 "crypto": [
  {
   "code": "BTC",
   "name": "ビットコイン",
   "price": 10169386,
   "high1y": 18838562,
   "drawdown": -46.0,
   "vs_ma": 0.8,
   "ret7": 6.8
  },
  {
   "code": "ETH",
   "name": "イーサリアム",
   "price": 284361,
   "high1y": 710063,
   "drawdown": -60.0,
   "vs_ma": 4.2,
   "ret7": 11.4
  }
 ]
}